fictionary/__init__.py
fictionary/cli.py
fictionary/markov.py
fictionary/model.py
fictionary/models/__init__.py
fictionary/models/all.txt
fictionary/models/american.txt
fictionary/models/british.txt
fictionary/models/words.txt
fictionary-0.1.0.dist-info/METADATA
fictionary-0.1.0.dist-info/RECORD
fictionary-0.1.0.dist-info/WHEEL
fictionary-0.1.0.dist-info/entry_points.txt
fictionary-0.1.0.dist-info/top_level.txt
