Metadata-Version: 2.1
Name: fictionary
Version: 0.1.0
Summary: Generate made-up words following the patterns used by real English words.
Home-page: https://github.com/judy2k/fictionary
Author: Mark Smith
Author-email: mark.smith@practicalpoetry.co.uk
License: MIT
Keywords: words dictionary fictionary
Platform: UNKNOWN
Classifier: Development Status :: 4 - Beta
Classifier: Environment :: Console
Classifier: License :: OSI Approved :: MIT License
Classifier: Natural Language :: English
Classifier: Operating System :: OS Independent
Classifier: Programming Language :: Python :: 2
Classifier: Programming Language :: Python :: 2.7
Classifier: Programming Language :: Python :: 3
Classifier: Programming Language :: Python :: 3.4
Classifier: Programming Language :: Python :: 3.5
Classifier: Programming Language :: Python :: 3.6
